{
  "project_info": {
    "project_number": "441347250440",
    "project_id": "mynotes-5d255",
    "storage_bucket": "mynotes-5d255.appspot.com"
  },
  "client": [
    {
      "client_info": {
        "mobilesdk_app_id": "1:441347250440:android:74fee86a6fa2f448afb4bd",
        "android_client_info": {
          "package_name": "com.example.mynotes"
        }
      },
      "oauth_client": [],
      "api_key": [
        {
          "current_key": "AIzaSyAgjERM1hPNuBb8AEBZVWZZiKjhj3ooHqU"
        }
      ],
      "services": {
        "appinvite_service": {
          "other_platform_oauth_client": []
        }
      }
    }
  ],
  "configuration_version": "1"
}